Vald_ForceDecks_API/ValdForceDecksAPI.py
Vald_ForceDecks_API/__init__.py
vald_ForceDecks_api-0.0.3.dist-info/METADATA
vald_ForceDecks_api-0.0.3.dist-info/WHEEL
vald_ForceDecks_api-0.0.3.dist-info/top_level.txt
vald_ForceDecks_api-0.0.3.dist-info/RECORD
