Metadata-Version: 2.1
Name: vald-ForceDecks-api
Version: 0.0.3
Summary: Python module to interact with VALD ForceDecks API.
Author: Régis Tremblay Lefrançois
Requires: requests
Requires-Dist: requests
